{"Metadata":{"errcode":"","fileStorage":"","errmsg":"","delta_context_value":"","changeAfterLastFetchTime":false,"conflict_policy":"","tables":[],"opstatus":0,"table":{"junction":false,"metadataObject":false,"updateable":false,"relationshipList":[],"columns":[{"updateable":true,"metadata":null,"nullable":false,"defaultValue":"","displayName":"idCelularSeguro","customizable":false,"description":"","nameField":false,"auditColumn":false,"datatype":"string","uiSequence":0,"table":"ClaveMovil","enumValues":[],"picklistValues":[],"custom":false,"length":40,"entityPageTemplateId":0,"fieldProperties":null,"sourceDatatype":"string","createable":false,"hasIndex":false,"fieldMappingId":0,"sourceFieldName":"","hasTranslation":false,"name":"idCelularSeguro","operationType":"","properties":[],"primaryKey":true},{"updateable":true,"metadata":null,"nullable":true,"defaultValue":"","displayName":"empresaCelular","customizable":false,"description":"","nameField":false,"auditColumn":false,"datatype":"string","uiSequence":0,"table":"ClaveMovil","enumValues":[],"picklistValues":[],"custom":false,"length":40,"entityPageTemplateId":0,"fieldProperties":null,"sourceDatatype":"string","createable":false,"hasIndex":false,"fieldMappingId":0,"sourceFieldName":"","hasTranslation":false,"name":"empresaCelular","operationType":"","properties":[],"primaryKey":false},{"updateable":true,"metadata":null,"nullable":true,"defaultValue":"","displayName":"codigoArea","customizable":false,"description":"","nameField":false,"auditColumn":false,"datatype":"string","uiSequence":0,"table":"ClaveMovil","enumValues":[],"picklistValues":[],"custom":false,"length":40,"entityPageTemplateId":0,"fieldProperties":null,"sourceDatatype":"string","createable":false,"hasIndex":false,"fieldMappingId":0,"sourceFieldName":"","hasTranslation":false,"name":"codigoArea","operationType":"","properties":[],"primaryKey":false},{"updateable":true,"metadata":null,"nullable":true,"defaultValue":"","displayName":"numeroCelular","customizable":false,"description":"","nameField":false,"auditColumn":false,"datatype":"string","uiSequence":0,"table":"ClaveMovil","enumValues":[],"picklistValues":[],"custom":false,"length":40,"entityPageTemplateId":0,"fieldProperties":null,"sourceDatatype":"string","createable":false,"hasIndex":false,"fieldMappingId":0,"sourceFieldName":"","hasTranslation":false,"name":"numeroCelular","operationType":"","properties":[],"primaryKey":false},{"updateable":true,"metadata":null,"nullable":true,"defaultValue":"","displayName":"codigo","customizable":false,"description":"","nameField":false,"auditColumn":false,"datatype":"string","uiSequence":0,"table":"ClaveMovil","enumValues":[],"picklistValues":[],"custom":false,"length":40,"entityPageTemplateId":0,"fieldProperties":null,"sourceDatatype":"string","createable":false,"hasIndex":false,"fieldMappingId":0,"sourceFieldName":"","hasTranslation":false,"name":"codigo","operationType":"","properties":[],"primaryKey":false},{"updateable":true,"metadata":null,"nullable":true,"defaultValue":"","displayName":"descripcion","customizable":false,"description":"","nameField":false,"auditColumn":false,"datatype":"string","uiSequence":0,"table":"ClaveMovil","enumValues":[],"picklistValues":[],"custom":false,"length":40,"entityPageTemplateId":0,"fieldProperties":null,"sourceDatatype":"string","createable":false,"hasIndex":false,"fieldMappingId":0,"sourceFieldName":"","hasTranslation":false,"name":"descripcion","operationType":"","properties":[],"primaryKey":false},{"updateable":true,"metadata":null,"nullable":true,"defaultValue":"","displayName":"pinSoftToken","customizable":false,"description":"","nameField":false,"auditColumn":false,"datatype":"string","uiSequence":0,"table":"ClaveMovil","enumValues":[],"picklistValues":[],"custom":false,"length":40,"entityPageTemplateId":0,"fieldProperties":null,"sourceDatatype":"string","createable":false,"hasIndex":false,"fieldMappingId":0,"sourceFieldName":"","hasTranslation":false,"name":"pinSoftToken","operationType":"","properties":[],"primaryKey":false},{"updateable":true,"metadata":null,"nullable":true,"defaultValue":"","displayName":"softToken","customizable":false,"description":"","nameField":false,"auditColumn":false,"datatype":"string","uiSequence":0,"table":"ClaveMovil","enumValues":[],"picklistValues":[],"custom":false,"length":40,"entityPageTemplateId":0,"fieldProperties":null,"sourceDatatype":"string","createable":false,"hasIndex":false,"fieldMappingId":0,"sourceFieldName":"","hasTranslation":false,"name":"softToken","operationType":"","properties":[],"primaryKey":false},{"updateable":true,"metadata":null,"nullable":true,"defaultValue":"","displayName":"idOperador","customizable":false,"description":"","nameField":false,"auditColumn":false,"datatype":"string","uiSequence":0,"table":"ClaveMovil","enumValues":[],"picklistValues":[],"custom":false,"length":40,"entityPageTemplateId":0,"fieldProperties":null,"sourceDatatype":"string","createable":false,"hasIndex":false,"fieldMappingId":0,"sourceFieldName":"","hasTranslation":false,"name":"idOperador","operationType":"","properties":[],"primaryKey":false},{"updateable":true,"metadata":null,"nullable":true,"defaultValue":"","displayName":"vigente","customizable":false,"description":"","nameField":false,"auditColumn":false,"datatype":"boolean","uiSequence":0,"table":"ClaveMovil","enumValues":[],"picklistValues":[],"custom":false,"length":0,"entityPageTemplateId":0,"fieldProperties":null,"sourceDatatype":"boolean","createable":false,"hasIndex":false,"fieldMappingId":0,"sourceFieldName":"","hasTranslation":false,"name":"vigente","operationType":"","properties":[],"primaryKey":false},{"updateable":true,"metadata":null,"nullable":true,"defaultValue":"","displayName":"codigoPais","customizable":false,"description":"","nameField":false,"auditColumn":false,"datatype":"string","uiSequence":0,"table":"ClaveMovil","enumValues":[],"picklistValues":[],"custom":false,"length":40,"entityPageTemplateId":0,"fieldProperties":null,"sourceDatatype":"string","createable":false,"hasIndex":false,"fieldMappingId":0,"sourceFieldName":"","hasTranslation":false,"name":"codigoPais","operationType":"","properties":[],"primaryKey":false},{"updateable":true,"metadata":null,"nullable":true,"defaultValue":"","displayName":"tipoSegundoFactor","customizable":false,"description":"","nameField":false,"auditColumn":false,"datatype":"string","uiSequence":0,"table":"ClaveMovil","enumValues":[],"picklistValues":[],"custom":false,"length":40,"entityPageTemplateId":0,"fieldProperties":null,"sourceDatatype":"string","createable":false,"hasIndex":false,"fieldMappingId":0,"sourceFieldName":"","hasTranslation":false,"name":"tipoSegundoFactor","operationType":"","properties":[],"primaryKey":false},{"updateable":true,"metadata":null,"nullable":true,"defaultValue":"","displayName":"segundoFactor","customizable":false,"description":"","nameField":false,"auditColumn":false,"datatype":"string","uiSequence":0,"table":"ClaveMovil","enumValues":[],"picklistValues":[],"custom":false,"length":40,"entityPageTemplateId":0,"fieldProperties":null,"sourceDatatype":"string","createable":false,"hasIndex":false,"fieldMappingId":0,"sourceFieldName":"","hasTranslation":false,"name":"segundoFactor","operationType":"","properties":[],"primaryKey":false}],"displayName":"","customizable":false,"deleteServiceId":"","description":"","createServiceId":"","selectServiceId":"","dataFilter":"","appId":"RBObjects","defaultEntity":false,"alias":"","uiconfigObject":false,"entityTypeID":0,"applicationName":"","updateServiceId":"","custom":false,"uniqueKeys":[],"label":"","partialUpdateServiceId":"","addedStandardFields":false,"name":"ClaveMovil","operationType":"","applicationId":0,"entityProperties":null,"sourceEntityName":"","primaryKey":["idCelularSeguro"]},"httpStatusCode":200,"namespaces":[],"timestamp":1685476912000}}